downloadyt/__init__.py
downloadyt/cli.py
downloadYTscript-0.1.0.dist-info/LICENSE
downloadYTscript-0.1.0.dist-info/METADATA
downloadYTscript-0.1.0.dist-info/WHEEL
downloadYTscript-0.1.0.dist-info/entry_points.txt
downloadYTscript-0.1.0.dist-info/top_level.txt
downloadYTscript-0.1.0.dist-info/RECORD
